{
  "_userProfileId": "USER-2",
  "_userProfileCreds": {
    "tag": "Credentials",
    "_userCredsName": "bob",
    "_userCredsPassword": "secret"
  },
  "_userProfileEmailAddr": "bob@example.com",
  "_userProfileEmailAddrVerified": "2022-08-02",
  "_userProfileDisplayName": "Bob",
  "_userProfileTosConsent": true,
  "_userProfileCompletion1": {
    "_userProfilePostalAddress": "Some street 1",
    "_userProfileTelephoneNbr": "(+32) 0000 00 00 00",
    "_userProfileAddrAndTelVerified": "2022-08-02"
  },
  "_userProfileCompletion2": {
    "_userProfileEId": "xxxx",
    "_userProfileEIdVerified": "2022-08-02"
  },
  "_userProfileRegistrationDate": 0,
  "_userProfileRights": [],
  "_userProfileAuthorizations": []
}
